django_orm_ext/__init__.py
django_orm_ext/django_orm_ext.py
django_orm_ext-1.3.0.dist-info/LICENSE
django_orm_ext-1.3.0.dist-info/METADATA
django_orm_ext-1.3.0.dist-info/WHEEL
django_orm_ext-1.3.0.dist-info/top_level.txt
django_orm_ext-1.3.0.dist-info/RECORD
